<?xml version="1.0" encoding="utf-8"?>
<iasettings>
  <projectproperties>
    <manufacturer>pselvaraj</manufacturer>
    <productname>CouthIntegration</productname>
    <productversion>1.0.0.0</productversion>
    <productcode>{eff1d70f-c625-4eb9-9dab-9c7ecbfaff80}</productcode>
    <upgradecode>{98471a62-f10a-41d8-b2c4-9b1c64473e6c}</upgradecode>
    <language>0</language>
    <languagename>English</languagename>
  </projectproperties>
  <summary>
    <title>CouthIntegration</title>
    <subject>CouthIntegration</subject>
    <author>pselvaraj</author>
    <summarycomments>CouthIntegration</summarycomments>
    <revisioncode>{644e14f0-c886-4610-9b7d-3b9f90678574}</revisioncode>
    <uacelevation>highestAvailable</uacelevation>
  </summary>
  <addremove>
    <publishername>pselvaraj</publishername>
    <contactname>pselvaraj</contactname>
    <helplink>http://www.mywebsite.com</helplink>
    <productupdatelink>http://www.mywebsite.com</productupdatelink>
    <addremovecomments>All Rights Reserved</addremovecomments>
    <iconfile />
  </addremove>
  <codegen>
    <generateincludefiles>1</generateincludefiles>
    <generatefeatures>0</generatefeatures>
    <refreshscript>0</refreshscript>
  </codegen>
  <compilervariables>
    <variables />
  </compilervariables>
  <build>
    <buildtype>0</buildtype>
  </build>
  <files>
    <filedetails filename="C:\Prakash\Projects\CRI\Couth\CouthIntegration\bin\Debug\CouthIntegration.exe" targetlocation="$TARGETDIR$" generatenativeimage="0" registerassembly="0" runinstallerclass="0" createshortcut="1" runprogram="1" installfilecommand="1" />
    <filedetails filename="C:\Prakash\Projects\CRI\Couth\TransferDatas\bin\Debug\TransferDatas.dll" targetlocation="$TARGETDIR$" generatenativeimage="0" registerassembly="0" runinstallerclass="0" createshortcut="0" runprogram="0" installfilecommand="0" />
  </files>
  <dependencies>
    <dependencydetails filename="C:\Program Files (x86)\Reference Assemblies\Microsoft\VBPowerPacks\v10.0\Microsoft.VisualBasic.PowerPacks.Vs.dll" targetlocation="GAC" generatenativeimage="0" registerassembly="0" runinstallerclass="0" createshortcut="0" runprogram="0" installfilecommand="0" />
    <dependencydetails filename="C:\Prakash\Projects\CRI\Couth\CouthIntegration\lib\Newtonsoft.Json.dll" targetlocation="$TARGETDIR$" generatenativeimage="0" registerassembly="0" runinstallerclass="0" createshortcut="0" runprogram="0" installfilecommand="0" />
    <dependencydetails filename="C:\Prakash\Projects\CRI\Couth\TransferDatas\bin\Debug\TransferDatas.dll" targetlocation="$TARGETDIR$" generatenativeimage="0" registerassembly="0" runinstallerclass="0" createshortcut="0" runprogram="0" installfilecommand="0" />
  </dependencies>
  <dialogtheme>
    <themename>Official</themename>
  </dialogtheme>
  <authenticode>
    <sign>0</sign>
    <certificatefile />
    <keyfile />
    <productinfourl />
    <authpassword />
    <timestampurl />
  </authenticode>
  <compression>
    <compressiontype>6</compressiontype>
    <encrypt>0</encrypt>
    <compressionpassword />
  </compression>
  <output>
    <outputtype>0</outputtype>
    <location />
    <filename />
    <calculatefilehash>0</calculatefilehash>
    <refreshrevisioncode>1</refreshrevisioncode>
  </output>
</iasettings>